Workbook
Name AllRevenue: Summary!$B$3:$B$12
Name GrandProfit: Summary!$D$13

Sheet Summary
A1: Department Summary
A2: Department | B2: Revenue | C2: Cost | D2: Profit | E2: Margin
A3: Dept1 | B3: ='Dept1'!B14 | C3: ='Dept1'!C14 | D3: ='Dept1'!D14 | E3: ='Dept1'!E14
A4: Dept2 | B4: ='Dept2'!B14 | C4: ='Dept2'!C14 | D4: ='Dept2'!D14 | E4: ='Dept2'!E14
A5: Dept3 | B5: ='Dept3'!B14 | C5: ='Dept3'!C14 | D5: ='Dept3'!D14 | E5: ='Dept3'!E14
A6: Dept4 | B6: ='Dept4'!B14 | C6: ='Dept4'!C14 | D6: ='Dept4'!D14 | E6: ='Dept4'!E14
A7: Dept5 | B7: ='Dept5'!B14 | C7: ='Dept5'!C14 | D7: ='Dept5'!D14 | E7: ='Dept5'!E14
A8: Dept6 | B8: ='Dept6'!B14 | C8: ='Dept6'!C14 | D8: ='Dept6'!D14 | E8: ='Dept6'!E14
A9: Dept7 | B9: ='Dept7'!B14 | C9: ='Dept7'!C14 | D9: ='Dept7'!D14 | E9: ='Dept7'!E14
A10: Dept8 | B10: ='Dept8'!B14 | C10: ='Dept8'!C14 | D10: ='Dept8'!D14 | E10: ='Dept8'!E14
A11: Dept9 | B11: ='Dept9'!B14 | C11: ='Dept9'!C14 | D11: ='Dept9'!D14 | E11: ='Dept9'!E14
A12: Dept10 | B12: ='Dept10'!B14 | C12: ='Dept10'!C14 | D12: ='Dept10'!D14 | E12: ='Dept10'!E14
A13: Grand Total | B13: =SUM(B3:B12) | C13: =SUM(C3:C12) | D13: =SUM(D3:D12) | E13: =IF(B13>0,D13/B13,0)

Sheet Dept1
A1: Month | B1: Revenue | C1: Cost | D1: Profit | E1: Margin
A2: 2026-01 | B2: 10500 | C2: 6300 | D2: =B2-C2 | E2: =IF(B2>0,D2/B2,0)
A3: 2026-02 | B3: 11000 | C3: 6600 | D3: =B3-C3 | E3: =IF(B3>0,D3/B3,0)
A4: 2026-03 | B4: 11500 | C4: 6900 | D4: =B4-C4 | E4: =IF(B4>0,D4/B4,0)
A5: 2026-04 | B5: 12000 | C5: 7200 | D5: =B5-C5 | E5: =IF(B5>0,D5/B5,0)
A6: 2026-05 | B6: 12500 | C6: 7500 | D6: =B6-C6 | E6: =IF(B6>0,D6/B6,0)
A7: 2026-06 | B7: 13000 | C7: 7800 | D7: =B7-C7 | E7: =IF(B7>0,D7/B7,0)
A8: 2026-07 | B8: 13500 | C8: 8100 | D8: =B8-C8 | E8: =IF(B8>0,D8/B8,0)
A9: 2026-08 | B9: 14000 | C9: 8400 | D9: =B9-C9 | E9: =IF(B9>0,D9/B9,0)
A10: 2026-09 | B10: 14500 | C10: 8700 | D10: =B10-C10 | E10: =IF(B10>0,D10/B10,0)
A11: 2026-10 | B11: 15000 | C11: 9000 | D11: =B11-C11 | E11: =IF(B11>0,D11/B11,0)
A12: 2026-11 | B12: 15500 | C12: 9300 | D12: =B12-C12 | E12: =IF(B12>0,D12/B12,0)
A13: 2026-12 | B13: 16000 | C13: 9600 | D13: =B13-C13 | E13: =IF(B13>0,D13/B13,0)
A14: Total | B14: =SUM(B2:B13) | C14: =SUM(C2:C13) | D14: =SUM(D2:D13) | E14: =IF(B14>0,D14/B14,0)

Sheet Dept2
A1: Month | B1: Revenue | C1: Cost | D1: Profit | E1: Margin
A2: 2026-01 | B2: 20500 | C2: 12300 | D2: =B2-C2 | E2: =IF(B2>0,D2/B2,0)
A3: 2026-02 | B3: 21000 | C3: 12600 | D3: =B3-C3 | E3: =IF(B3>0,D3/B3,0)
A4: 2026-03 | B4: 21500 | C4: 12900 | D4: =B4-C4 | E4: =IF(B4>0,D4/B4,0)
A5: 2026-04 | B5: 22000 | C5: 13200 | D5: =B5-C5 | E5: =IF(B5>0,D5/B5,0)
A6: 2026-05 | B6: 22500 | C6: 13500 | D6: =B6-C6 | E6: =IF(B6>0,D6/B6,0)
A7: 2026-06 | B7: 23000 | C7: 13800 | D7: =B7-C7 | E7: =IF(B7>0,D7/B7,0)
A8: 2026-07 | B8: 23500 | C8: 14100 | D8: =B8-C8 | E8: =IF(B8>0,D8/B8,0)
A9: 2026-08 | B9: 24000 | C9: 14400 | D9: =B9-C9 | E9: =IF(B9>0,D9/B9,0)
A10: 2026-09 | B10: 24500 | C10: 14700 | D10: =B10-C10 | E10: =IF(B10>0,D10/B10,0)
A11: 2026-10 | B11: 25000 | C11: 15000 | D11: =B11-C11 | E11: =IF(B11>0,D11/B11,0)
A12: 2026-11 | B12: 25500 | C12: 15300 | D12: =B12-C12 | E12: =IF(B12>0,D12/B12,0)
A13: 2026-12 | B13: 26000 | C13: 15600 | D13: =B13-C13 | E13: =IF(B13>0,D13/B13,0)
A14: Total | B14: =SUM(B2:B13) | C14: =SUM(C2:C13) | D14: =SUM(D2:D13) | E14: =IF(B14>0,D14/B14,0)

Sheet Dept3
A1: Month | B1: Revenue | C1: Cost | D1: Profit | E1: Margin
A2: 2026-01 | B2: 30500 | C2: 18300 | D2: =B2-C2 | E2: =IF(B2>0,D2/B2,0)
A3: 2026-02 | B3: 31000 | C3: 18600 | D3: =B3-C3 | E3: =IF(B3>0,D3/B3,0)
A4: 2026-03 | B4: 31500 | C4: 18900 | D4: =B4-C4 | E4: =IF(B4>0,D4/B4,0)
A5: 2026-04 | B5: 32000 | C5: 19200 | D5: =B5-C5 | E5: =IF(B5>0,D5/B5,0)
A6: 2026-05 | B6: 32500 | C6: 19500 | D6: =B6-C6 | E6: =IF(B6>0,D6/B6,0)
A7: 2026-06 | B7: 33000 | C7: 19800 | D7: =B7-C7 | E7: =IF(B7>0,D7/B7,0)
A8: 2026-07 | B8: 33500 | C8: 20100 | D8: =B8-C8 | E8: =IF(B8>0,D8/B8,0)
A9: 2026-08 | B9: 34000 | C9: 20400 | D9: =B9-C9 | E9: =IF(B9>0,D9/B9,0)
A10: 2026-09 | B10: 34500 | C10: 20700 | D10: =B10-C10 | E10: =IF(B10>0,D10/B10,0)
A11: 2026-10 | B11: 35000 | C11: 21000 | D11: =B11-C11 | E11: =IF(B11>0,D11/B11,0)
A12: 2026-11 | B12: 35500 | C12: 21300 | D12: =B12-C12 | E12: =IF(B12>0,D12/B12,0)
A13: 2026-12 | B13: 36000 | C13: 21600 | D13: =B13-C13 | E13: =IF(B13>0,D13/B13,0)
A14: Total | B14: =SUM(B2:B13) | C14: =SUM(C2:C13) | D14: =SUM(D2:D13) | E14: =IF(B14>0,D14/B14,0)

Sheet Dept4
A1: Month | B1: Revenue | C1: Cost | D1: Profit | E1: Margin
A2: 2026-01 | B2: 40500 | C2: 24300 | D2: =B2-C2 | E2: =IF(B2>0,D2/B2,0)
A3: 2026-02 | B3: 41000 | C3: 24600 | D3: =B3-C3 | E3: =IF(B3>0,D3/B3,0)
A4: 2026-03 | B4: 41500 | C4: 24900 | D4: =B4-C4 | E4: =IF(B4>0,D4/B4,0)
A5: 2026-04 | B5: 42000 | C5: 25200 | D5: =B5-C5 | E5: =IF(B5>0,D5/B5,0)
A6: 2026-05 | B6: 42500 | C6: 25500 | D6: =B6-C6 | E6: =IF(B6>0,D6/B6,0)
A7: 2026-06 | B7: 43000 | C7: 25800 | D7: =B7-C7 | E7: =IF(B7>0,D7/B7,0)
A8: 2026-07 | B8: 43500 | C8: 26100 | D8: =B8-C8 | E8: =IF(B8>0,D8/B8,0)
A9: 2026-08 | B9: 44000 | C9: 26400 | D9: =B9-C9 | E9: =IF(B9>0,D9/B9,0)
A10: 2026-09 | B10: 44500 | C10: 26700 | D10: =B10-C10 | E10: =IF(B10>0,D10/B10,0)
A11: 2026-10 | B11: 45000 | C11: 27000 | D11: =B11-C11 | E11: =IF(B11>0,D11/B11,0)
A12: 2026-11 | B12: 45500 | C12: 27300 | D12: =B12-C12 | E12: =IF(B12>0,D12/B12,0)
A13: 2026-12 | B13: 46000 | C13: 27600 | D13: =B13-C13 | E13: =IF(B13>0,D13/B13,0)
A14: Total | B14: =SUM(B2:B13) | C14: =SUM(C2:C13) | D14: =SUM(D2:D13) | E14: =IF(B14>0,D14/B14,0)

Sheet Dept5
A1: Month | B1: Revenue | C1: Cost | D1: Profit | E1: Margin
A2: 2026-01 | B2: 50500 | C2: 30300 | D2: =B2-C2 | E2: =IF(B2>0,D2/B2,0)
A3: 2026-02 | B3: 51000 | C3: 30600 | D3: =B3-C3 | E3: =IF(B3>0,D3/B3,0)
A4: 2026-03 | B4: 51500 | C4: 30900 | D4: =B4-C4 | E4: =IF(B4>0,D4/B4,0)
A5: 2026-04 | B5: 52000 | C5: 31200 | D5: =B5-C5 | E5: =IF(B5>0,D5/B5,0)
A6: 2026-05 | B6: 52500 | C6: 31500 | D6: =B6-C6 | E6: =IF(B6>0,D6/B6,0)
A7: 2026-06 | B7: 53000 | C7: 31800 | D7: =B7-C7 | E7: =IF(B7>0,D7/B7,0)
A8: 2026-07 | B8: 53500 | C8: 32100 | D8: =B8-C8 | E8: =IF(B8>0,D8/B8,0)
A9: 2026-08 | B9: 54000 | C9: 32400 | D9: =B9-C9 | E9: =IF(B9>0,D9/B9,0)
A10: 2026-09 | B10: 54500 | C10: 32700 | D10: =B10-C10 | E10: =IF(B10>0,D10/B10,0)
A11: 2026-10 | B11: 55000 | C11: 33000 | D11: =B11-C11 | E11: =IF(B11>0,D11/B11,0)
A12: 2026-11 | B12: 55500 | C12: 33300 | D12: =B12-C12 | E12: =IF(B12>0,D12/B12,0)
A13: 2026-12 | B13: 56000 | C13: 33600 | D13: =B13-C13 | E13: =IF(B13>0,D13/B13,0)
A14: Total | B14: =SUM(B2:B13) | C14: =SUM(C2:C13) | D14: =SUM(D2:D13) | E14: =IF(B14>0,D14/B14,0)

Sheet Dept6
A1: Month | B1: Revenue | C1: Cost | D1: Profit | E1: Margin
A2: 2026-01 | B2: 60500 | C2: 36300 | D2: =B2-C2 | E2: =IF(B2>0,D2/B2,0)
A3: 2026-02 | B3: 61000 | C3: 36600 | D3: =B3-C3 | E3: =IF(B3>0,D3/B3,0)
A4: 2026-03 | B4: 61500 | C4: 36900 | D4: =B4-C4 | E4: =IF(B4>0,D4/B4,0)
A5: 2026-04 | B5: 62000 | C5: 37200 | D5: =B5-C5 | E5: =IF(B5>0,D5/B5,0)
A6: 2026-05 | B6: 62500 | C6: 37500 | D6: =B6-C6 | E6: =IF(B6>0,D6/B6,0)
A7: 2026-06 | B7: 63000 | C7: 37800 | D7: =B7-C7 | E7: =IF(B7>0,D7/B7,0)
A8: 2026-07 | B8: 63500 | C8: 38100 | D8: =B8-C8 | E8: =IF(B8>0,D8/B8,0)
A9: 2026-08 | B9: 64000 | C9: 38400 | D9: =B9-C9 | E9: =IF(B9>0,D9/B9,0)
A10: 2026-09 | B10: 64500 | C10: 38700 | D10: =B10-C10 | E10: =IF(B10>0,D10/B10,0)
A11: 2026-10 | B11: 65000 | C11: 39000 | D11: =B11-C11 | E11: =IF(B11>0,D11/B11,0)
A12: 2026-11 | B12: 65500 | C12: 39300 | D12: =B12-C12 | E12: =IF(B12>0,D12/B12,0)
A13: 2026-12 | B13: 66000 | C13: 39600 | D13: =B13-C13 | E13: =IF(B13>0,D13/B13,0)
A14: Total | B14: =SUM(B2:B13) | C14: =SUM(C2:C13) | D14: =SUM(D2:D13) | E14: =IF(B14>0,D14/B14,0)

Sheet Dept7
A1: Month | B1: Revenue | C1: Cost | D1: Profit | E1: Margin
A2: 2026-01 | B2: 70500 | C2: 42300 | D2: =B2-C2 | E2: =IF(B2>0,D2/B2,0)
A3: 2026-02 | B3: 71000 | C3: 42600 | D3: =B3-C3 | E3: =IF(B3>0,D3/B3,0)
A4: 2026-03 | B4: 71500 | C4: 42900 | D4: =B4-C4 | E4: =IF(B4>0,D4/B4,0)
A5: 2026-04 | B5: 72000 | C5: 43200 | D5: =B5-C5 | E5: =IF(B5>0,D5/B5,0)
A6: 2026-05 | B6: 72500 | C6: 43500 | D6: =B6-C6 | E6: =IF(B6>0,D6/B6,0)
A7: 2026-06 | B7: 73000 | C7: 43800 | D7: =B7-C7 | E7: =IF(B7>0,D7/B7,0)
A8: 2026-07 | B8: 73500 | C8: 44100 | D8: =B8-C8 | E8: =IF(B8>0,D8/B8,0)
A9: 2026-08 | B9: 74000 | C9: 44400 | D9: =B9-C9 | E9: =IF(B9>0,D9/B9,0)
A10: 2026-09 | B10: 74500 | C10: 44700 | D10: =B10-C10 | E10: =IF(B10>0,D10/B10,0)
A11: 2026-10 | B11: 75000 | C11: 45000 | D11: =B11-C11 | E11: =IF(B11>0,D11/B11,0)
A12: 2026-11 | B12: 75500 | C12: 45300 | D12: =B12-C12 | E12: =IF(B12>0,D12/B12,0)
A13: 2026-12 | B13: 76000 | C13: 45600 | D13: =B13-C13 | E13: =IF(B13>0,D13/B13,0)
A14: Total | B14: =SUM(B2:B13) | C14: =SUM(C2:C13) | D14: =SUM(D2:D13) | E14: =IF(B14>0,D14/B14,0)

Sheet Dept8
A1: Month | B1: Revenue | C1: Cost | D1: Profit | E1: Margin
A2: 2026-01 | B2: 80500 | C2: 48300 | D2: =B2-C2 | E2: =IF(B2>0,D2/B2,0)
A3: 2026-02 | B3: 81000 | C3: 48600 | D3: =B3-C3 | E3: =IF(B3>0,D3/B3,0)
A4: 2026-03 | B4: 81500 | C4: 48900 | D4: =B4-C4 | E4: =IF(B4>0,D4/B4,0)
A5: 2026-04 | B5: 82000 | C5: 49200 | D5: =B5-C5 | E5: =IF(B5>0,D5/B5,0)
A6: 2026-05 | B6: 82500 | C6: 49500 | D6: =B6-C6 | E6: =IF(B6>0,D6/B6,0)
A7: 2026-06 | B7: 83000 | C7: 49800 | D7: =B7-C7 | E7: =IF(B7>0,D7/B7,0)
A8: 2026-07 | B8: 83500 | C8: 50100 | D8: =B8-C8 | E8: =IF(B8>0,D8/B8,0)
A9: 2026-08 | B9: 84000 | C9: 50400 | D9: =B9-C9 | E9: =IF(B9>0,D9/B9,0)
A10: 2026-09 | B10: 84500 | C10: 50700 | D10: =B10-C10 | E10: =IF(B10>0,D10/B10,0)
A11: 2026-10 | B11: 85000 | C11: 51000 | D11: =B11-C11 | E11: =IF(B11>0,D11/B11,0)
A12: 2026-11 | B12: 85500 | C12: 51300 | D12: =B12-C12 | E12: =IF(B12>0,D12/B12,0)
A13: 2026-12 | B13: 86000 | C13: 51600 | D13: =B13-C13 | E13: =IF(B13>0,D13/B13,0)
A14: Total | B14: =SUM(B2:B13) | C14: =SUM(C2:C13) | D14: =SUM(D2:D13) | E14: =IF(B14>0,D14/B14,0)

Sheet Dept9
A1: Month | B1: Revenue | C1: Cost | D1: Profit | E1: Margin
A2: 2026-01 | B2: 90500 | C2: 54300 | D2: =B2-C2 | E2: =IF(B2>0,D2/B2,0)
A3: 2026-02 | B3: 91000 | C3: 54600 | D3: =B3-C3 | E3: =IF(B3>0,D3/B3,0)
A4: 2026-03 | B4: 91500 | C4: 54900 | D4: =B4-C4 | E4: =IF(B4>0,D4/B4,0)
A5: 2026-04 | B5: 92000 | C5: 55200 | D5: =B5-C5 | E5: =IF(B5>0,D5/B5,0)
A6: 2026-05 | B6: 92500 | C6: 55500 | D6: =B6-C6 | E6: =IF(B6>0,D6/B6,0)
A7: 2026-06 | B7: 93000 | C7: 55800 | D7: =B7-C7 | E7: =IF(B7>0,D7/B7,0)
A8: 2026-07 | B8: 93500 | C8: 56100 | D8: =B8-C8 | E8: =IF(B8>0,D8/B8,0)
A9: 2026-08 | B9: 94000 | C9: 56400 | D9: =B9-C9 | E9: =IF(B9>0,D9/B9,0)
A10: 2026-09 | B10: 94500 | C10: 56700 | D10: =B10-C10 | E10: =IF(B10>0,D10/B10,0)
A11: 2026-10 | B11: 95000 | C11: 57000 | D11: =B11-C11 | E11: =IF(B11>0,D11/B11,0)
A12: 2026-11 | B12: 95500 | C12: 57300 | D12: =B12-C12 | E12: =IF(B12>0,D12/B12,0)
A13: 2026-12 | B13: 96000 | C13: 57600 | D13: =B13-C13 | E13: =IF(B13>0,D13/B13,0)
A14: Total | B14: =SUM(B2:B13) | C14: =SUM(C2:C13) | D14: =SUM(D2:D13) | E14: =IF(B14>0,D14/B14,0)

Sheet Dept10
A1: Month | B1: Revenue | C1: Cost | D1: Profit | E1: Margin
A2: 2026-01 | B2: 100500 | C2: 60300 | D2: =B2-C2 | E2: =IF(B2>0,D2/B2,0)
A3: 2026-02 | B3: 101000 | C3: 60600 | D3: =B3-C3 | E3: =IF(B3>0,D3/B3,0)
A4: 2026-03 | B4: 101500 | C4: 60900 | D4: =B4-C4 | E4: =IF(B4>0,D4/B4,0)
A5: 2026-04 | B5: 102000 | C5: 61200 | D5: =B5-C5 | E5: =IF(B5>0,D5/B5,0)
A6: 2026-05 | B6: 102500 | C6: 61500 | D6: =B6-C6 | E6: =IF(B6>0,D6/B6,0)
A7: 2026-06 | B7: 103000 | C7: 61800 | D7: =B7-C7 | E7: =IF(B7>0,D7/B7,0)
A8: 2026-07 | B8: 103500 | C8: 62100 | D8: =B8-C8 | E8: =IF(B8>0,D8/B8,0)
A9: 2026-08 | B9: 104000 | C9: 62400 | D9: =B9-C9 | E9: =IF(B9>0,D9/B9,0)
A10: 2026-09 | B10: 104500 | C10: 62700 | D10: =B10-C10 | E10: =IF(B10>0,D10/B10,0)
A11: 2026-10 | B11: 105000 | C11: 63000 | D11: =B11-C11 | E11: =IF(B11>0,D11/B11,0)
A12: 2026-11 | B12: 105500 | C12: 63300 | D12: =B12-C12 | E12: =IF(B12>0,D12/B12,0)
A13: 2026-12 | B13: 106000 | C13: 63600 | D13: =B13-C13 | E13: =IF(B13>0,D13/B13,0)
A14: Total | B14: =SUM(B2:B13) | C14: =SUM(C2:C13) | D14: =SUM(D2:D13) | E14: =IF(B14>0,D14/B14,0)
